odoo/addons/contract_update_last_date_invoiced/README.rst
odoo/addons/contract_update_last_date_invoiced/__init__.py
odoo/addons/contract_update_last_date_invoiced/__manifest__.py
odoo/addons/contract_update_last_date_invoiced/i18n/contract_update_last_date_invoiced.pot
odoo/addons/contract_update_last_date_invoiced/i18n/es.po
odoo/addons/contract_update_last_date_invoiced/i18n/fr.po
odoo/addons/contract_update_last_date_invoiced/i18n/it.po
odoo/addons/contract_update_last_date_invoiced/i18n/nl.po
odoo/addons/contract_update_last_date_invoiced/models/__init__.py
odoo/addons/contract_update_last_date_invoiced/models/contract_line.py
odoo/addons/contract_update_last_date_invoiced/readme/CONFIGURATION.rst
odoo/addons/contract_update_last_date_invoiced/readme/CONTRIBUTORS.md
odoo/addons/contract_update_last_date_invoiced/readme/DESCRIPTION.md
odoo/addons/contract_update_last_date_invoiced/readme/USAGE.md
odoo/addons/contract_update_last_date_invoiced/security/security.xml
odoo/addons/contract_update_last_date_invoiced/static/description/icon.png
odoo/addons/contract_update_last_date_invoiced/static/description/index.html
odoo/addons/contract_update_last_date_invoiced/tests/__init__.py
odoo/addons/contract_update_last_date_invoiced/tests/test_contract_update_last_date_invoiced.py
odoo/addons/contract_update_last_date_invoiced/views/contract_line.xml
odoo/addons/contract_update_last_date_invoiced/views/contract_views.xml
odoo/addons/contract_update_last_date_invoiced/wizards/__init__.py
odoo/addons/contract_update_last_date_invoiced/wizards/update_last_date_invoiced.py
odoo/addons/contract_update_last_date_invoiced/wizards/update_last_date_invoiced.xml
odoo_addon_contract_update_last_date_invoiced-18.0.1.0.1.3.dist-info/METADATA
odoo_addon_contract_update_last_date_invoiced-18.0.1.0.1.3.dist-info/WHEEL
odoo_addon_contract_update_last_date_invoiced-18.0.1.0.1.3.dist-info/top_level.txt
odoo_addon_contract_update_last_date_invoiced-18.0.1.0.1.3.dist-info/RECORD
