Metadata-Version: 2.1
Name: odoo-addon-contract_update_last_date_invoiced
Version: 18.0.1.0.1.3
Requires-Python: >=3.10
Requires-Dist: odoo-addon-contract==18.0.*
Requires-Dist: odoo==18.0.*
Summary: This module allows to update the last date invoiced if invoices are deleted.
Home-page: https://github.com/OCA/contract
License: AGPL-3
Author: ACSONE SA/NV,Odoo Community Association (OCA)
Author-email: support@odoo-community.org
Classifier: Programming Language :: Python
Classifier: Framework :: Odoo
Classifier: Framework :: Odoo :: 18.0
Classifier: License :: OSI Approved :: GNU Affero General Public License v3
